{
  "vix": {
    "price": 17.38,
    "prev": 18.29,
    "change_pct": -4.98,
    "change_bps": null,
    "date": "2026-05-05"
  },
  "oil": {
    "price": 109.76,
    "prev": 105.38,
    "change_pct": 4.16,
    "change_bps": null,
    "date": "2026-05-04"
  },
  "tnx": {
    "price": 4.43,
    "prev": 4.45,
    "change_pct": -0.45,
    "change_bps": null,
    "date": "2026-05-05"
  },
  "hy": {
    "price": 277.0,
    "prev": 278.0,
    "change_pct": null,
    "change_bps": -1.0,
    "date": "2026-05-05"
  },
  "ig": {
    "price": 99.0,
    "prev": 101.0,
    "change_pct": null,
    "change_bps": -2.0,
    "date": "2026-05-05"
  },
  "sp_ma": {
    "ma50": 6836.0,
    "ma200": 6738.0,
    "death_cross": false
  },
  "updated_utc": "2026-05-06T22:51:12Z"
}